iotemplatelib/__init__.py
iotemplatelib/__init__.pyi
iotemplatelib/io_glob.py
iotemplatelib/io_glob.pyi
iotemplatelib/io_logger.py
iotemplatelib/io_logger.pyi
iotemplatelib/io_settings.py
iotemplatelib/io_settings.pyi
iotemplatelib/py.typed
iotemplatelib-1.0.4.dist-info/LICENSE.md
iotemplatelib-1.0.4.dist-info/METADATA
iotemplatelib-1.0.4.dist-info/WHEEL
iotemplatelib-1.0.4.dist-info/top_level.txt
iotemplatelib-1.0.4.dist-info/RECORD
