Metadata-Version: 2.1
Name: iotemplatelib
Version: 1.0.4
Summary: TBD
Author-email: Team IO-Aero <info@io-aero.com>
Maintainer-email: Team IO-Aero <info@io-aero.ch>
Project-URL: Bug Tracker, https://github.com/io-aero/io-template-lib/issues
Project-URL: Documentation, https://io-aero.github.io/io-template-lib/
Project-URL: Homepage, https://github.com/io-aero/io-template-lib
Project-URL: Release History, https://io-aero.github.io/io-template-lib/release_history/
Project-URL: Release Notes, https://io-aero.github.io/io-template-lib/release_notes/
Project-URL: Source, https://github.com/io-aero/io-template-lib/iotemplatelib/
Keywords: TBD,TBD
Classifier: Development Status :: 5 - Production/Stable
Classifier: Environment :: Console
Classifier: Intended Audience :: Science/Research
Classifier: License :: Other/Proprietary License
Classifier: Programming Language :: Python :: 3.10
Classifier: Topic :: Scientific/Engineering
Classifier: Typing :: Typed
Requires-Python: >=3.10
License-File: LICENSE.md
